[
  {
    "id": 1,
    "question": "當活塞在上死點時，活塞頂端與汽缸蓋之間剩餘的汽缸容積，稱為燃燒室容積",
    "options": [
      "O",
      "X"
    ],
    "answer": 0,
    "noShuffle": true
  },
  {
    "id": 2,
    "question": "TCS 是在緊急煞車時防止車輪鎖住， ABS 是在濕滑路面起步或加速時防止驅動輪打滑",
    "options": [
      "O",
      "X"
    ],
    "answer": 0,
    "noShuffle": true,
    "freeScore": true
  },
  {
    "id": 3,
    "question": "油電混合動力車輛在起步與低速狀態下，是採用引擎模式",
    "options": [
      "O",
      "X"
    ],
    "answer": 0,
    "noShuffle": true,
    "freeScore": true
  },
  {
    "id": 4,
    "question": "起動安全開關是防止變速箱不在空檔或引擎在運轉中使起動系統產生作用發生危險及損壞馬達小齒輪與飛輪環齒輪的安全裝置",
    "options": [
      "O",
      "X"
    ],
    "answer": 0,
    "noShuffle": true
  },
  {
    "id": 5,
    "question": "汽車網路系統傳輸可簡化線束、減輕重量、縮小尺寸，但增加成本",
    "options": [
      "O",
      "X"
    ],
    "answer": 0,
    "noShuffle": true,
    "freeScore": true
  },
  {
    "id": 6,
    "question": "一般車輛暖氣設備的熱源為引擎冷卻水",
    "options": [
      "O",
      "X"
    ],
    "answer": 0,
    "noShuffle": true
  },
  {
    "id": 7,
    "question": "汽油引擎電子控制噴射系統之含氧感知器是用來感測進氣中的氧氣濃度",
    "options": [
      "O",
      "X"
    ],
    "answer": 0,
    "noShuffle": true,
    "freeScore": true
  },
  {
    "id": 8,
    "question": "柴油引擎使用增壓器可以增加容積效率，提昇引擎輸出馬力",
    "options": [
      "O",
      "X"
    ],
    "answer": 0,
    "noShuffle": true
  },
  {
    "id": 9,
    "question": "動力轉向系統之發展，其主要目的為減少引擎的動力損失，故採用動力轉向裝置，可以獲得較大的轉向角度",
    "options": [
      "O",
      "X"
    ],
    "answer": 0,
    "noShuffle": true,
    "freeScore": true
  },
  {
    "id": 10,
    "question": "駐車煞車警告燈，在駐車煞車完全釋放後燈應熄滅，若駐車煞車完全釋放而警告燈仍未熄滅，表示煞車系統異常或煞車油液面太低",
    "options": [
      "O",
      "X"
    ],
    "answer": 0,
    "noShuffle": true
  },
  {
    "id": 11,
    "question": "多數車輛測量自動變速箱內潤滑油之油量時，應在引擎發動至正常工作溫度，怠速時以量尺測試之",
    "options": [
      "O",
      "X"
    ],
    "answer": 0,
    "noShuffle": true
  },
  {
    "id": 12,
    "question": "油箱上有加油口及密封式油箱蓋，可使油箱內能保持大氣壓力並保持送油順暢",
    "options": [
      "O",
      "X"
    ],
    "answer": 0,
    "noShuffle": true
  },
  {
    "id": 13,
    "question": "具有後輪，其前端附掛於曳引車第五輪的拖車，稱為半拖車",
    "options": [
      "O",
      "X"
    ],
    "answer": 0,
    "noShuffle": true
  },
  {
    "id": 14,
    "question": "電子煞車力分配系統 EBD 可有效抑制車輛過度轉向或轉向不足等失控的現象發生，或因轉向不足致車輛向外側滑移，或轉向過度致車輛橫越道路中心線",
    "options": [
      "O",
      "X"
    ],
    "answer": 0,
    "noShuffle": true,
    "freeScore": true
  },
  {
    "id": 15,
    "question": "壓縮比高的引擎，所產生的動力較大，容易產生爆震及空氣污染，故須使用低辛烷值汽油",
    "options": [
      "O",
      "X"
    ],
    "answer": 0,
    "noShuffle": true,
    "freeScore": true
  },
  {
    "id": 16,
    "question": "電動汽車是利用貯蓄於電池的電，驅動馬達做為汽車的動力裝置，同時是零排放物質、低噪音，且能大幅減低二氧化碳",
    "options": [
      "O",
      "X"
    ],
    "answer": 0,
    "noShuffle": true
  },
  {
    "id": 17,
    "question": "一般低速柴油引擎的熱力循環是等壓循環",
    "options": [
      "O",
      "X"
    ],
    "answer": 0,
    "noShuffle": true
  },
  {
    "id": 18,
    "question": "車輛差速器的功用是產生差速作用，防止輪胎拖曳和減少輪胎磨耗，能使車輛在轉彎時，內側輪加速，外側輪減速",
    "options": [
      "O",
      "X"
    ],
    "answer": 0,
    "noShuffle": true,
    "freeScore": true
  },
  {
    "id": 19,
    "question": "液壓煞車所使用煞車油，其沸點高低，不會影響煞車性能",
    "options": [
      "O",
      "X"
    ],
    "answer": 0,
    "noShuffle": true,
    "freeScore": true
  },
  {
    "id": 20,
    "question": "電瓶使用之電水係用鹽酸與蒸餾水配製而成",
    "options": [
      "O",
      "X"
    ],
    "answer": 0,
    "noShuffle": true,
    "freeScore": true
  },
  {
    "id": 21,
    "question": "危險警告燈的電源須經點火開關，並使用原來方向燈的燈泡及轉向信號指示燈",
    "options": [
      "O",
      "X"
    ],
    "answer": 0,
    "noShuffle": true,
    "freeScore": true
  },
  {
    "id": 22,
    "question": "離合器位於引擎與變速箱間，能使引擎動力與傳動系統接合或分離",
    "options": [
      "O",
      "X"
    ],
    "answer": 0,
    "noShuffle": true
  },
  {
    "id": 23,
    "question": "水冷式引擎冷卻系統，當冷卻水溫達正常工作溫度時，節溫器關閉，使引擎水套與水箱間相通，冷卻水便流經水箱循環",
    "options": [
      "O",
      "X"
    ],
    "answer": 0,
    "noShuffle": true,
    "freeScore": true
  },
  {
    "id": 24,
    "question": "一般獨立式前懸吊系統，為防止車輛轉彎時車身向外傾斜翻滾的趨勢，裝置有穩定桿",
    "options": [
      "O",
      "X"
    ],
    "answer": 0,
    "noShuffle": true
  },
  {
    "id": 25,
    "question": "車輛轉向系統除傳統液壓式外，較新款的設計有電動馬達轉向系統及液壓式電動邦浦轉向系統",
    "options": [
      "O",
      "X"
    ],
    "answer": 0,
    "noShuffle": true
  },
  {
    "id": 26,
    "question": "汽車充電系統中，當引擎發動中充電指示燈仍亮著是表示",
    "options": [
      "在充電狀態",
      "充電系統異常",
      "電瓶故障",
      "冷氣系統異常"
    ],
    "answer": 1
  },
  {
    "id": 27,
    "question": "將方向盤的旋轉力經轉向齒輪，傳到拉桿以擺動前輪左右轉向之組件為",
    "options": [
      "平穩桿",
      "轉向機",
      "驅動桿",
      "轉向柱"
    ],
    "answer": 3
  },
  {
    "id": 28,
    "question": "不具有汽車特種功能之車種",
    "options": [
      "拖吊車",
      "聯結車",
      "消防車",
      "雲梯車"
    ],
    "answer": 1
  },
  {
    "id": 29,
    "question": "轉向系統總成中與駕駛人最密切者為",
    "options": [
      "方向盤",
      "轉向柱",
      "轉向齒輪",
      "直拉桿"
    ],
    "answer": 0
  },
  {
    "id": 30,
    "question": "在汽缸中做往復運動，將燃燒產生的動力經活塞銷及連桿而傳到曲軸，使曲軸做迴轉運動的是",
    "options": [
      "火星塞",
      "傳動桿",
      "活塞",
      "凸輪軸"
    ],
    "answer": 2
  },
  {
    "id": 31,
    "question": "用來支撐車輛重量及載重量的機構為",
    "options": [
      "懸吊系統",
      "傳動系統",
      "轉向系統",
      "車身及車架"
    ],
    "answer": 0
  },
  {
    "id": 32,
    "question": "汽油引擎發生爆震原因為",
    "options": [
      "引擎壓縮比變低",
      "汽油辛烷值過低",
      "混合氣溫度及壓力過低",
      "汽油辛烷值過高"
    ],
    "answer": 1
  },
  {
    "id": 33,
    "question": "點火線圈之作用係將電瓶的電壓轉變為",
    "options": [
      "12V 電壓",
      "低壓電",
      "交流電",
      "高壓電"
    ],
    "answer": 3
  },
  {
    "id": 34,
    "question": "目前大客車多採用",
    "options": [
      "前置引擎前輪驅動式",
      "後置引擎後輪驅動式",
      "前置引擎後輪驅動式",
      "中置引擎後輪驅動式"
    ],
    "answer": 1
  },
  {
    "id": 35,
    "question": "傳動軸之滑動接頭的功用是 ______ 時異音",
    "options": [
      "改變傳動方向",
      "調整傳動軸長度以適應路況",
      "減少車體震動",
      "適應車速變化減少下坡"
    ],
    "answer": 1
  },
  {
    "id": 36,
    "question": "交流發電機整流器能將靜子線圈產生的 ______ 相交流電，全波整流成直流電後輸出",
    "options": [
      "單",
      "雙",
      "三",
      "四"
    ],
    "answer": 2
  },
  {
    "id": 37,
    "question": "下列何者不是飛輪的功能",
    "options": [
      "使引擎能夠運轉平穩",
      "動力行程時吸收並暫存動能",
      "可增加引擎轉速",
      "可減少震動"
    ],
    "answer": 2
  },
  {
    "id": 38,
    "question": "汽車前輪校正項目中，為使車輛轉向後具有良好的回復性為",
    "options": [
      "前束",
      "內傾角",
      "外傾角",
      "轉向前展"
    ],
    "answer": 1
  },
  {
    "id": 39,
    "question": "引擎所產生機械功與所消耗燃料，兩者的熱值之比，稱為",
    "options": [
      "壓縮比",
      "引擎效率",
      "熱效率",
      "燃油效率"
    ],
    "answer": 2
  },
  {
    "id": 40,
    "question": "輪胎之編號為 205/60SR15 91H 其 205 表示",
    "options": [
      "輪胎直徑",
      "輪胎高度",
      "扁平比",
      "輪胎寬度"
    ],
    "answer": 3
  },
  {
    "id": 41,
    "question": "四行程引擎的曲軸旋轉 ______ 才完成一次循環",
    "options": [
      "360°",
      "720°",
      "120°",
      "180°"
    ],
    "answer": 1
  },
  {
    "id": 42,
    "question": "更換汽車起動馬達時應先拆卸:",
    "options": [
      "起動馬達 ST 接頭",
      "起動馬達固定螺桿",
      "起動馬達 M 接頭",
      "電瓶負極線"
    ],
    "answer": 3
  },
  {
    "id": 43,
    "question": "柴油引擎進氣行程吸入",
    "options": [
      "柴油",
      "二氧化碳",
      "混合汽",
      "純空氣"
    ],
    "answer": 3
  },
  {
    "id": 44,
    "question": "汽車煞車系統，其中液壓煞車係利用巴斯噶原理和液體之",
    "options": [
      "可壓縮性",
      "槓桿原理",
      "不可壓縮性",
      "熱導性"
    ],
    "answer": 2
  },
  {
    "id": 45,
    "question": "下列何者不是汽車行車紀錄器的功能？",
    "options": [
      "瞬間速度之記錄",
      "車輛位置之記錄",
      "行走時間之記錄",
      "行走距離之記錄"
    ],
    "answer": 1
  },
  {
    "id": 46,
    "question": "汽車行駛道路，所受地面衝擊與震動，由何種機件吸收",
    "options": [
      "轉向裝置",
      "傳動軸",
      "懸吊裝置",
      "後軸總成"
    ],
    "answer": 2
  },
  {
    "id": 47,
    "question": "引擎運轉時，溫度最高之機件為",
    "options": [
      "活塞",
      "連桿",
      "排氣門",
      "曲軸"
    ],
    "answer": 2
  },
  {
    "id": 48,
    "question": "柴油引擎在壓縮行程是壓縮",
    "options": [
      "純空氣",
      "空氣與柴油的混合氣",
      "純柴油",
      "先壓縮空氣再壓縮柴油"
    ],
    "answer": 0
  },
  {
    "id": 49,
    "question": "當發電機發出電壓低於電瓶電壓時，電瓶供給全車電器設備用電，稱為",
    "options": [
      "充電",
      "最大電壓",
      "再充電",
      "放電"
    ],
    "answer": 3
  },
  {
    "id": 50,
    "question": "電腦直接點火系統不包含",
    "options": [
      "點火線圈",
      "分電盤",
      "點火控制器",
      "曲軸位置感知器"
    ],
    "answer": 1
  }
]
