[
  {
    "id": 1,
    "question": "柴油引擎燃燒時產生之最高壓力約為汽油引擎之二倍，故同馬力之柴油引擎較汽油引擎為重且精密，致整體引擎製造成本較高",
    "options": [
      "O",
      "X"
    ],
    "answer": 0,
    "noShuffle": true
  },
  {
    "id": 2,
    "question": "汽油引擎四行程中之壓縮行程，其壓縮的目的，能使混合氣均勻、溫度增高、燃燒容易，提昇引擎效率",
    "options": [
      "O",
      "X"
    ],
    "answer": 0,
    "noShuffle": true
  },
  {
    "id": 3,
    "question": "電壓錶一定要和電器(負荷)並聯",
    "options": [
      "O",
      "X"
    ],
    "answer": 0,
    "noShuffle": true
  },
  {
    "id": 4,
    "question": "量測汽油引擎汽缸壓縮壓力時應在冷引擎下實施",
    "options": [
      "O",
      "X"
    ],
    "answer": 1,
    "noShuffle": true
  },
  {
    "id": 5,
    "question": "孔型噴油嘴多使用於直接噴射式柴油引擎",
    "options": [
      "O",
      "X"
    ],
    "answer": 0,
    "noShuffle": true
  },
  {
    "id": 6,
    "question": "一般汽油引擎壓縮比約為 8~14:1 ，而柴油引擎約在 17~25:1 ",
    "options": [
      "O",
      "X"
    ],
    "answer": 0,
    "noShuffle": true
  },
  {
    "id": 7,
    "question": "柴油引擎當噴射壓力過低時，霧化不良，引擎易排黑煙，並產生爆震現象",
    "options": [
      "O",
      "X"
    ],
    "answer": 0,
    "noShuffle": true
  },
  {
    "id": 8,
    "question": "引擎缸數愈多，動力重疊度數愈大，飛輪所需儲存動力愈大",
    "options": [
      "O",
      "X"
    ],
    "answer": 1,
    "noShuffle": true
  },
  {
    "id": 9,
    "question": "電腦控制共軌式柴油引擎可以減少 CO 、 HC 、 NOX 及粒狀污染物(PM) 的排出量",
    "options": [
      "O",
      "X"
    ],
    "answer": 0,
    "noShuffle": true
  },
  {
    "id": 10,
    "question": "壓縮比高的引擎，所產生的動力較大，惟易生爆震及空氣污染，故須用低辛烷值汽油",
    "options": [
      "O",
      "X"
    ],
    "answer": 1,
    "noShuffle": true
  },
  {
    "id": 11,
    "question": "活塞每移動一個行程的長度等於兩倍曲軸臂的長度，亦即等於曲軸臂旋轉圓周的直徑",
    "options": [
      "O",
      "X"
    ],
    "answer": 0,
    "noShuffle": true
  },
  {
    "id": 12,
    "question": "車輛轉彎或行駛高低不平路面時，左右兩輪速度不同，是由差速器產生作用",
    "options": [
      "O",
      "X"
    ],
    "answer": 0,
    "noShuffle": true
  },
  {
    "id": 13,
    "question": "單作用式避震器之主要功用是吸收彈簧回彈力量",
    "options": [
      "O",
      "X"
    ],
    "answer": 0,
    "noShuffle": true
  },
  {
    "id": 14,
    "question": "輪胎氣壓太低，會使胎面中央易磨耗",
    "options": [
      "O",
      "X"
    ],
    "answer": 1,
    "noShuffle": true
  },
  {
    "id": 15,
    "question": "後傾角的功用是使汽車在行駛中穩定前輪的方向",
    "options": [
      "O",
      "X"
    ],
    "answer": 0,
    "noShuffle": true
  },
  {
    "id": 16,
    "question": "超速離合器主要功用，是當引擎發動後，飛輪與馬達齒輪自動分離，以防止馬達損壞",
    "options": [
      "O",
      "X"
    ],
    "answer": 0,
    "noShuffle": true
  },
  {
    "id": 17,
    "question": "汽油引擎的最大馬力及扭力均在引擎轉速最高時",
    "options": [
      "O",
      "X"
    ],
    "answer": 1,
    "noShuffle": true
  },
  {
    "id": 18,
    "question": "汽車冷氣系統中冷凝器的作用為吸收車廂內之熱，降低空氣溫度",
    "options": [
      "O",
      "X"
    ],
    "answer": 1,
    "noShuffle": true
  },
  {
    "id": 19,
    "question": "車輪定位的目的是在提高行車穩定性，使轉向容易，防止震動、側滑、輪胎拖曳等現象",
    "options": [
      "O",
      "X"
    ],
    "answer": 0,
    "noShuffle": true
  },
  {
    "id": 20,
    "question": "一般電瓶充電應採用快速充電法，才能延長電瓶的壽命",
    "options": [
      "O",
      "X"
    ],
    "answer": 1,
    "noShuffle": true
  },
  {
    "id": 21,
    "question": "使用液化石油氣(簡稱 L.P.G)其辛烷值較汽油",
    "options": [
      "低",
      "高",
      "不一定",
      "視溫度"
    ],
    "answer": 1
  },
  {
    "id": 22,
    "question": "汽油引擎產生爆震下列何者非其原因",
    "options": [
      "引擎過熱",
      "汽缸內積碳太多",
      "點火時間太晚",
      "混合器太稀"
    ],
    "answer": 0,
    "freeScore": true
  },
  {
    "id": 23,
    "question": "進汽門早開晚關的目的是",
    "options": [
      "進氣充分增加動力",
      "減少爆震",
      "防止漏氣",
      "使汽門不易損壞"
    ],
    "answer": 0
  },
  {
    "id": 24,
    "question": "以四行程引擎為例，若進汽門早開 10 度，晚關 35 度，則實際壓縮行程應為 ______ 度",
    "options": [
      "225",
      "180",
      "135",
      "145"
    ],
    "answer": 3
  },
  {
    "id": 25,
    "question": "標示 215/50/R16 的輪胎， 16 代表",
    "options": [
      "胎寬 16 吋",
      "輪胎內徑 16 吋",
      "胎寬為胎璧厚度的 1.6 倍",
      "高寬比 16"
    ],
    "answer": 1
  },
  {
    "id": 26,
    "question": "檢查自動變速箱油量時",
    "options": [
      "引擎應熄火",
      "引擎應發動選擇桿可置於任意位置",
      "引擎應發動選擇桿排至各檔後置於 P 或 N",
      "引擎發動與否均可"
    ],
    "answer": 2
  },
  {
    "id": 27,
    "question": "ATF 為下列何種油料簡稱",
    "options": [
      "機油",
      "煞車油",
      "自動變速箱油",
      "汽油"
    ],
    "answer": 2
  },
  {
    "id": 28,
    "question": "下列何者不是充電系統基本機件",
    "options": [
      "起動馬達",
      "發電機",
      "調整器",
      "充電指示燈或電流錶及連接各電器間之導線"
    ],
    "answer": 0
  },
  {
    "id": 29,
    "question": "有關電錶的敘述，下列何者有誤",
    "options": [
      "三用電錶測量範圍包括整流粒之檢查",
      "三用電錶測量範圍包括電阻的測量",
      "電壓錶一定要和電器(負荷)串聯",
      "電流錶使用時應與電器(負荷)串聯"
    ],
    "answer": 2
  },
  {
    "id": 30,
    "question": "踩下離合器踏板時，引擎動力没有傳到那一個機件？",
    "options": [
      "飛輪",
      "離合器壓板",
      "離合器片",
      "釋放軸承"
    ],
    "answer": 2
  },
  {
    "id": 31,
    "question": "將 3 歐姆及 6 歐姆兩個電阻並聯後再和 4 歐姆電阻串聯，接通於 2A 之電流時，則端電壓為",
    "options": [
      "12V",
      "18V",
      "24V",
      "26V"
    ],
    "answer": 0
  },
  {
    "id": 32,
    "question": "傳動軸上萬向接頭的功用為",
    "options": [
      "增加傳動軸的扭力",
      "配合傳動軸的長度變化",
      "配合傳動軸的角度變化",
      "改變傳動軸之轉動方向"
    ],
    "answer": 2
  },
  {
    "id": 33,
    "question": "液體扭力變換接合器使用於",
    "options": [
      "普通變速箱",
      "手動變速箱",
      "自動變速箱",
      "同步式變速箱"
    ],
    "answer": 2
  },
  {
    "id": 34,
    "question": "麥花臣式前懸吊系統又名 ______ 懸吊系統",
    "options": [
      "整體式",
      "獨立式",
      "擺動式",
      "雞胸骨式"
    ],
    "answer": 0,
    "freeScore": true
  },
  {
    "id": 35,
    "question": "引擎點火順序為 1-3-4-2 ，當第三缸在壓縮行程時，則第四缸為",
    "options": [
      "進氣行程",
      "壓縮行程",
      "動力行程",
      "排氣行程"
    ],
    "answer": 0
  },
  {
    "id": 36,
    "question": "火星塞",
    "options": [
      "電極間隙愈大，跳火電壓愈低",
      "電極形狀愈尖，跳火電壓愈高",
      "汽缸內壓力愈高，跳火電壓愈低",
      "電極溫度愈高，跳火電壓愈低"
    ],
    "answer": 3
  },
  {
    "id": 37,
    "question": "下列何者非電晶體點火系統優點",
    "options": [
      "能供電壓高",
      "保養少",
      "點火提前反應迅速",
      "能供電壓低"
    ],
    "answer": 3
  },
  {
    "id": 38,
    "question": "汽車冷氣機之冷媒，在進入壓縮機前為",
    "options": [
      "高壓高溫氣態",
      "高壓中溫氣態",
      "低壓低溫氣態",
      "低壓低溫液態"
    ],
    "answer": 2
  },
  {
    "id": 39,
    "question": "當點火開關開啟至 ON 時，溫度錶便開始偵測 ______ 中冷卻水溫度",
    "options": [
      "水箱",
      "水套",
      "節溫器",
      "副水箱"
    ],
    "answer": 1
  },
  {
    "id": 40,
    "question": "充電中的電瓶遇火花容易引起爆炸，因為充電中的電瓶會產生",
    "options": [
      "氧氣",
      "氮氣",
      "氫氣",
      "硫"
    ],
    "answer": 2
  }
]
