[
  {
    "id": 1,
    "question": "小客貨兩用車係指總重量在 3,500 公斤以下，或全部座位在 9 座以下，並最後一排座椅固定後，後方實際之載貨空間達 ______ 立方公尺以上之汽車",
    "options": [
      "1",
      "2",
      "3",
      "4"
    ],
    "answer": 0
  },
  {
    "id": 2,
    "question": "最後軸中心點與車尾間之距離，但保險桿不計在內稱為",
    "options": [
      "輪距",
      "軸距",
      "後懸",
      "段差"
    ],
    "answer": 2
  },
  {
    "id": 3,
    "question": "具有特種裝置之特種車，後懸不得超過軸距百分之 66.6 。但承載客貨部分不得超過軸距百分之",
    "options": [
      "40",
      "50",
      "55",
      "60"
    ],
    "answer": 1
  },
  {
    "id": 4,
    "question": "小客車係指座位在 9 座以下之客車或座位在 ______ 座以下之幼童專用車，其座位之計算包括駕駛人及幼童管理人在內",
    "options": [
      "20",
      "22",
      "24",
      "25"
    ],
    "answer": 2
  },
  {
    "id": 5,
    "question": "申請汽車駕駛執照考驗路考未及格者，得於下次申請考驗時免考筆試，其免考期限為",
    "options": [
      "1 個月",
      "2 個月",
      "3 個月",
      "1 年"
    ],
    "answer": 3
  },
  {
    "id": 6,
    "question": "小型汽車置放架，如裝置於車輛後側，其長度不應超過後側車身外:",
    "options": [
      "25 公分",
      "30 公分",
      "50 公分",
      "60 公分"
    ],
    "answer": 2
  },
  {
    "id": 7,
    "question": "汽車或拖車因交通事故遭受重大損壞，經送廠修復者，應申請實施",
    "options": [
      "無須檢驗",
      "定期檢驗",
      "新領牌照檢驗",
      "臨時檢驗"
    ],
    "answer": 3
  },
  {
    "id": 8,
    "question": "乙類大客車係指軸距未逾 4 公尺且核定總重量逾 ______ 噸之大客車",
    "options": [
      "3",
      "3.5",
      "4",
      "4.5"
    ],
    "answer": 3
  },
  {
    "id": 9,
    "question": "貨車裝載貨物高度自地面算起，大型車不得超過 ______ 公尺",
    "options": [
      "3",
      "3.5",
      "4",
      "4.5"
    ],
    "answer": 2
  },
  {
    "id": 10,
    "question": "依道路交通管理處罰條例第 43 條規定，駕駛汽車有拆除消音器，或以其他方式造成噪音之情形者，除處駕駛人新臺幣 6,000 至 36,000 元罰鍰，於 1 年內再度違反者，並吊扣其駕駛執照",
    "options": [
      "3 個月",
      "4 個月",
      "6 個月",
      "1 年"
    ],
    "answer": 2
  },
  {
    "id": 11,
    "question": "大型重型機車行駛於快速公路前，應妥為檢查車輛，在行駛途中輪胎胎紋深度任一點不得不足 ______ 公釐",
    "options": [
      "1",
      "1.3",
      "1.5",
      "1.6"
    ],
    "answer": 0
  },
  {
    "id": 12,
    "question": "禁制標線區分為縱向標線、橫向標線、輔助標線，下列何者不屬於輔助標線?",
    "options": [
      "槽化線",
      "網狀線",
      "停止線",
      "機慢車停等區線"
    ],
    "answer": 2
  },
  {
    "id": 13,
    "question": "汽機車駕駛人，駕駛汽機車經測試檢定吐氣所含酒精濃度達每公升 0.25 毫克或血液中酒精濃度達百分之 0.05 以上，年滿 ______ 之同車乘客處新臺幣 6,000 至 15,000 元罰鍰。但年滿 70 歲、心智障礙或汽車運輸業之乘客，不在此限",
    "options": [
      "4 歲",
      "16 歲",
      "18 歲",
      "20 歲"
    ],
    "answer": 2
  },
  {
    "id": 14,
    "question": "不依規定接受道路交通安全講習者，處新台幣 1,800 元罰鍰。經再通知依限參加講習，逾期 6 個月以上仍不參加者，吊扣其駕駛執照 ______ 個月",
    "options": [
      "1",
      "3",
      "4",
      "6"
    ],
    "answer": 3
  },
  {
    "id": 15,
    "question": "依道路交通管理處罰條例第 31 條第 4 項規定，汽車駕駛人對於 ______ 以下或需要特別看護之兒童，單獨留置於車內者，處駕駛人新台幣 3,000 元罰鍰，並施以 3 小時道路交通安全講習",
    "options": [
      "5 歲",
      "6 歲",
      "7 歲",
      "8 歲"
    ],
    "answer": 1
  },
  {
    "id": 16,
    "question": "汽車未依規定裝設行車紀錄器者，處汽車所有人新台幣 ______ 罰鍰",
    "options": [
      "12,000 至 24,000 元",
      "2,000 至 3,000 元",
      "3,500 至 5,000 元",
      "600 至 1,000 元"
    ],
    "answer": 0
  },
  {
    "id": 17,
    "question": "汽車駕駛人，連續駕車超過 ______ 經查屬實，或患病足以影響安全駕駛者，處新臺幣 1,200 至 2,400 元罰鍰，並禁止其駕駛",
    "options": [
      "5 小時",
      "8 小時",
      "10 小時",
      "12 小時"
    ],
    "answer": 1
  },
  {
    "id": 18,
    "question": "道路交通管理處罰條例規定，汽車未領用有效牌照、懸掛他車號牌或未懸掛號牌於道路停車者，依第 12 條第 1 項規定處罰外，",
    "options": [
      "汽車並吊銷其牌照",
      "汽車並扣繳其牌照",
      "汽車並當場移置保管",
      "汽車並當場移置保管及扣繳其牌照"
    ],
    "answer": 3
  },
  {
    "id": 19,
    "question": "大型車行駛於高速公路，行經長度 4 公里以上之隧道，至少應保持 ______ 公尺以上之行車安全距離",
    "options": [
      "30",
      "50",
      "80",
      "100"
    ],
    "answer": 3
  },
  {
    "id": 20,
    "question": "駕駛執照吊扣期間再駕駛小型車者，除處罰鍰，並當場禁止其駕駛外，並應",
    "options": [
      "再吊扣駕照 3 個月",
      "再吊扣駕照 1 年",
      "再吊扣駕照 3 年",
      "吊銷駕駛執照"
    ],
    "answer": 3
  },
  {
    "id": 21,
    "question": "汽車行駛於夜間交會時，除應保持安全間隔外，應使用",
    "options": [
      "遠光燈",
      "近光燈",
      "危險警告燈",
      "霧燈"
    ],
    "answer": 1
  },
  {
    "id": 22,
    "question": "汽車引擎、底盤、電系、車門損壞，行駛時顯有危險而不即行停駛修復者，應處汽車所有人罰鍰，並扣留其牌照，責令修復檢驗合格後發還之。檢驗不合格，經確認不堪使用者，責令",
    "options": [
      "繳銷",
      "報廢",
      "過戶",
      "停駛"
    ],
    "answer": 1
  },
  {
    "id": 23,
    "question": "指車輛因上、下人、客，裝卸物品，其停止時間未滿 3 分鐘，保持立即行駛之狀態，稱為:",
    "options": [
      "行駛",
      "停車",
      "臨時停車",
      "以上皆非"
    ],
    "answer": 2
  },
  {
    "id": 24,
    "question": "汽車裝置高音量喇叭或其他產生噪音器物，應依最高額處罰外，該高音量喇叭或噪音器物",
    "options": [
      "發還",
      "應沒入",
      "變賣抵繳",
      "任意處理"
    ],
    "answer": 1
  },
  {
    "id": 25,
    "question": "汽車駕駛人違規停車遭逕行舉發，每逾 ______ 得連續舉發",
    "options": [
      "30 分鐘",
      "1 小時",
      "2 小時",
      "3 小時"
    ],
    "answer": 2
  },
  {
    "id": 26,
    "question": "汽車駕駛人，駕車在鐵路平交道臨時停車，處新臺幣 15,000 至 90,000 元罰鍰。因而肇事者，",
    "options": [
      "吊扣駕駛執照 3 個月",
      "吊銷駕駛執照",
      "註銷駕駛執照",
      "吊扣駕駛執照 4 年"
    ],
    "answer": 1
  },
  {
    "id": 27,
    "question": "汽車所有人違反道路交通管理處罰條例，經吊銷或註銷者，須滿 ______ ，且經公路主管機關檢驗合格後，始得再行請領其汽車牌照",
    "options": [
      "1 個月",
      "3 個月",
      "5 個月",
      "6 個月"
    ],
    "answer": 3
  },
  {
    "id": 28,
    "question": "受處罰人接獲違反道路交通管理事件通知單後，於 ______ 日內得不經裁決，逕依第 92 條第 4 項之罰鍰基準規定，向指定之處所繳納結案",
    "options": [
      "30",
      "45",
      "60",
      "90"
    ],
    "answer": 0
  },
  {
    "id": 29,
    "question": "大型重型機車及機車臨時停車時，應依車輛順行方向緊靠道路邊緣停放，其前輪或後輪外側距離緣石或路面邊緣不得逾 ______ 公分",
    "options": [
      "20",
      "30",
      "40",
      "50"
    ],
    "answer": 2
  },
  {
    "id": 30,
    "question": "汽車行經高速公路，停放服務區、休息站內逾 ______ ，除應予拖、吊、移置、保管、處理外，並應予以舉發處罰",
    "options": [
      "1 小時",
      "2 小時",
      "3 小時",
      "4 小時"
    ],
    "answer": 3
  },
  {
    "id": 31,
    "question": "車道線用以劃分各線車道，指示車輛駕駛人循車道行駛。本標線為 ______ ，線段長 4 公尺，間距 6 公尺，線寬 10 公分",
    "options": [
      "白虛線",
      "白實線",
      "黃虛線",
      "黄實線"
    ],
    "answer": 0
  },
  {
    "id": 32,
    "question": "表示「警告」，車輛應減速接近，注意安全，小心通過之行車管制號誌為",
    "options": [
      "圓形綠燈",
      "圓形紅燈",
      "閃光黃燈",
      "閃光紅燈"
    ],
    "answer": 2
  },
  {
    "id": 33,
    "question": "大型重型機車之汽缸總排氣量 ______ 立方公分以上，在公告開放其行駛之高速公路路段及時段，不受高速公路及快速公路交通管制規則第 19 條第 1 項第 4 款不得行駛及進入高速公路之限制",
    "options": [
      "250",
      "350",
      "500",
      "550"
    ],
    "answer": 3
  },
  {
    "id": 34,
    "question": "半聯結車全長不得超過",
    "options": [
      "16 公尺",
      "18 公尺",
      "20 公尺",
      "12 公尺"
    ],
    "answer": 1
  },
  {
    "id": 35,
    "question": "用以促使車輛駕駛人及行人瞭解道路上之特殊狀況、提高警覺，並準備防範應變之措施之作用標誌係指",
    "options": [
      "禁制標誌",
      "警告標誌",
      "指示標誌",
      "輔助標誌"
    ],
    "answer": 1
  },
  {
    "id": 36,
    "question": "「省道路線編號」之指示標誌體形為",
    "options": [
      "八角形",
      "梅花形",
      "盾形",
      "方形"
    ],
    "answer": 2
  },
  {
    "id": 37,
    "question": "汽車駕駛人在道路收費停車處所停車，未依規定繳費，主管機關應書面通知駕駛人於 ______ 日內補繳，並收取必要之工本費用，逾期再不繳納，處新臺幣 300 元罰鍰",
    "options": [
      "3",
      "5",
      "7",
      "10"
    ],
    "answer": 2
  },
  {
    "id": 38,
    "question": "汽車行駛於道路上，其駕駛人、前座或小型車後座乘客應依規定繫安全帶，違者處罰駕駛人。但營業大客車、計程車或租賃車輛代僱駕駛人已盡告知義務，乘客仍未繫安全帶時，則",
    "options": [
      "處罰汽車駕駛人",
      "處罰該乘客",
      "處罰汽車所有人",
      "不用處罰該乘客"
    ],
    "answer": 1
  },
  {
    "id": 39,
    "question": "道路交通安全規則係依據 ______ 第 92 條第 1 項規定訂定之",
    "options": [
      "公路法",
      "高速公路及快速公路管制規則",
      "道路交通管理處罰條例",
      "汽車運輸業管理規則"
    ],
    "answer": 2
  },
  {
    "id": 40,
    "question": "汽車駕駛人，在道路交通標誌前臨時停車，遮蔽標誌者，處新臺幣 300 至 600 元罰鍰，但接送未滿 ______ 歲之兒童、行動不便之人上、下車者，臨時停車不受 3 分鐘之限制",
    "options": [
      "5",
      "6",
      "7",
      "8"
    ],
    "answer": 2
  },
  {
    "id": 41,
    "question": "自中華民國 102 年 1 月 1 日起，下列車輛之行車執照須申請換發？",
    "options": [
      "救護車",
      "幼童專用車",
      "機車",
      "校車"
    ],
    "answer": [
      0,
      1,
      3
    ]
  },
  {
    "id": 42,
    "question": "後懸之敘述何者正確？",
    "options": [
      "最後軸中心點與車尾間之距離，但保險桿不計在內",
      "客車不得超過軸距 60%",
      "貨車及客貨兩用車不得超過軸距 60%",
      "具有特種裝置之特種車不得超過軸距 66.6%"
    ],
    "answer": [
      0,
      1,
      3
    ]
  },
  {
    "id": 43,
    "question": "汽車定期檢驗以出廠年份計算，何者正確？",
    "options": [
      "拖車未滿 3 年免予檢驗",
      "自用小客車及營業小客車滿 5 年以上者每年至少檢驗 1 次",
      "租賃期 1 年以上租賃自用小客車出廠年份未滿 3 年者免予定期檢驗",
      "逾 10 年之營業大客車於指定日期前一個月內檢驗"
    ],
    "answer": [
      2,
      3
    ]
  },
  {
    "id": 44,
    "question": "汽車行駛於高速公路長度 4 公里以上之隧道，應遵守之下列規定 ______ 公里時，所有車輛應保持 20 公尺以上之行車安全距離",
    "options": [
      "隧道內應開亮頭燈",
      "小型車應保持 40 公尺以上之行車安全距離",
      "大型車應保持 100 公尺以上之行車安全距離",
      "隧道內道路壅塞導致車速低於每小時 20"
    ],
    "answer": [
      0,
      2,
      3
    ]
  },
  {
    "id": 45,
    "question": "有關汽車座位立位之核定規定，下列何者錯誤 ______ 得超過 2 個座位",
    "options": [
      "小客車不得設立位",
      "大客車車內高度未達 180 公分，不得設立位",
      "幼童專用車不得設立位",
      "貨車駕駛室，連駕駛人座位不"
    ],
    "answer": [
      1,
      3
    ]
  },
  {
    "id": 46,
    "question": "下列執行任務中之汽車在同向二車道以上之道路時，除應依標誌或標線之指示行駛外， ______ 均可行駛內外側車道",
    "options": [
      "消防車",
      "救護車",
      "警備車",
      "教練車"
    ],
    "answer": [
      0,
      1,
      2
    ]
  },
  {
    "id": 47,
    "question": "汽車辦理下列哪些登記， ______ 得申請汽車主要駕駛人登記",
    "options": [
      "新領牌照",
      "過戶",
      "報廢",
      "復駛"
    ],
    "answer": [
      0,
      1,
      3
    ]
  },
  {
    "id": 48,
    "question": "下列哪些車輛 ______ 行駛於長陡坡之下坡路段，除有特殊狀況外，應行駛外側車道，並禁止變換車道",
    "options": [
      "載重之大貨車",
      "大客貨兩用車",
      "載重之小貨車",
      "聯結車"
    ],
    "answer": [],
    "freeScore": true
  },
  {
    "id": 49,
    "question": "有下列情形者，應設置警告標誌",
    "options": [
      "急彎路段",
      "險坡路段",
      "交岔路口",
      "道路施工路段"
    ],
    "answer": [
      0,
      1,
      2,
      3
    ]
  },
  {
    "id": 50,
    "question": "汽車駕駛人駕駛汽車有下列情形者， ______ 規定之最高時速 30 公里，處新臺幣 6,000 至 36,000 元罰鍰，並當場禁止其駕駛",
    "options": [
      "在道路上蛇行",
      "拆除消音器",
      "以其他危險方式駕車",
      "行車速度，超過"
    ],
    "answer": [
      0,
      1,
      2
    ]
  }
]
